django_wysiwyg/__init__.py
django_wysiwyg/models.py
django_wysiwyg/utils.py
django_wysiwyg/templates/django_wysiwyg/alloyeditor/editor_instance.html
django_wysiwyg/templates/django_wysiwyg/alloyeditor/includes.html
django_wysiwyg/templates/django_wysiwyg/ckeditor/editor_instance.html
django_wysiwyg/templates/django_wysiwyg/ckeditor/includes.html
django_wysiwyg/templates/django_wysiwyg/froala/editor_instance.html
django_wysiwyg/templates/django_wysiwyg/froala/includes.html
django_wysiwyg/templates/django_wysiwyg/redactor/editor_instance.html
django_wysiwyg/templates/django_wysiwyg/redactor/includes.html
django_wysiwyg/templates/django_wysiwyg/tinymce/editor_instance.html
django_wysiwyg/templates/django_wysiwyg/tinymce/includes.html
django_wysiwyg/templates/django_wysiwyg/tinymce_advanced/editor_instance.html
django_wysiwyg/templates/django_wysiwyg/tinymce_advanced/includes.html
django_wysiwyg/templates/django_wysiwyg/yui/editor_instance.html
django_wysiwyg/templates/django_wysiwyg/yui/includes.html
django_wysiwyg/templates/django_wysiwyg/yui_advanced/editor_instance.html
django_wysiwyg/templates/django_wysiwyg/yui_advanced/includes.html
django_wysiwyg/templates/my-app-name/admin/change_form.html
django_wysiwyg/templatetags/__init__.py
django_wysiwyg/templatetags/wysiwyg.py
django_wysiwyg-0.8.0.dist-info/DESCRIPTION.rst
django_wysiwyg-0.8.0.dist-info/METADATA
django_wysiwyg-0.8.0.dist-info/RECORD
django_wysiwyg-0.8.0.dist-info/WHEEL
django_wysiwyg-0.8.0.dist-info/metadata.json
django_wysiwyg-0.8.0.dist-info/top_level.txt
