Metadata-Version: 1.1
Name: django-wysiwyg
Version: 0.8.0
Summary: django-wysiwyg
Home-page: https://github.com/pydanny/django-wysiwyg
Author: Daniel Greenfeld, Chris Adams, Diederik van der Boor
Author-email: pydanny@gmail.com
License: MIT
Keywords: django,wysiwyg,redactor,ckeditor,tinymce,froala
Platform: UNKNOWN
Classifier: Development Status :: 4 - Beta
Classifier: Environment :: Web Environment
Classifier: Framework :: Django
Classifier: License :: OSI Approved :: MIT License
Classifier: Operating System :: OS Independent
Classifier: Programming Language :: JavaScript
Classifier: Programming Language :: Python
Classifier: Programming Language :: Python :: 2.6
Classifier: Programming Language :: Python :: 2.7
Classifier: Programming Language :: Python :: 3.3
Classifier: Programming Language :: Python :: 3.4
Classifier: Programming Language :: Python :: 3.5
Classifier: Topic :: Internet :: WWW/HTTP :: Browsers
Classifier: Topic :: Internet :: WWW/HTTP :: Site Management
Classifier: Topic :: Office/Business :: Office Suites
Classifier: Topic :: Software Development :: Libraries :: Python Modules
Classifier: Topic :: Software Development :: User Interfaces
Classifier: Topic :: Text Editors :: Word Processors
Classifier: Topic :: Text Processing :: Fonts
Classifier: Topic :: Text Processing :: Markup :: HTML
